rapidpro_flows-1.2.9.dist-info/DESCRIPTION.rst
rapidpro_flows-1.2.9.dist-info/METADATA
rapidpro_flows-1.2.9.dist-info/metadata.json
rapidpro_flows-1.2.9.dist-info/RECORD
rapidpro_flows-1.2.9.dist-info/top_level.txt
rapidpro_flows-1.2.9.dist-info/WHEEL
temba_flows/__init__.py
temba_flows/exceptions.py
temba_flows/runner.py
temba_flows/tests.py
temba_flows/utils.py
temba_flows/definition/__init__.py
temba_flows/definition/actions.py
temba_flows/definition/flow.py
temba_flows/definition/tests.py
