Metadata-Version: 2.0
Name: rapidpro-flows
Version: 1.2.9
Summary: Python implementation of the RapidPro flow engine
Home-page: https://github.com/rapidpro/flows
Author: Nyaruka
Author-email: code@nyaruka.com
License: BSD
Keywords: rapidpro flows
Platform: UNKNOWN
Classifier: Development Status :: 4 - Beta
Classifier: Intended Audience :: Developers
Classifier: Topic :: Software Development :: Libraries
Classifier: License :: OSI Approved :: BSD License
Classifier: Programming Language :: Python :: 2
Requires-Dist: enum34 (==1.0.4)
Requires-Dist: ordered-set (==1.4.0)
Requires-Dist: phonenumbers (==7.0.2)
Requires-Dist: pytz
Requires-Dist: rapidpro-expressions (==1.1.6)
Requires-Dist: regex (==2015.10.05)
